[
  {
    "text": "Truyện A Clash Of Kings Cập Nhật Chương Mới",
    "time": "2025-10-23T15:42:00Z"
  },
  {
    "text": "Bạn đã nhận được huy hiệu 'Độc Giả Trung Thành' ",
    "time": "2025-10-20T12:00:00Z"
  },
  
    {
    "text": "Bạn đã nhận được huy hiệu 'Độc Giả Trung Thành' ",
    "time": "2025-10-20T12:00:00Z"
  },
  {
    "text": "Truyện Attack on Titan – chương cuối đã ra mắt!",
    "time": "2025-10-13T21:00:00Z"
  },
  {
    "text": "Truyện A Storm Of Storms Cập Nhật Chương Mới",
    "time": "2025-10-10T07:30:00Z"
  },
  {
    "text": "Cập nhật ứng dụng: Thêm tính năng bình luận và thông báo đẩy!",
    "time": "2025-10-08T14:05:00Z"
  }
]
